tgbotzero/__about__.py
tgbotzero/__init__.py
tgbotzero/__main__.py
tgbotzero/examples/00_echo_bot.py
tgbotzero/examples/01_bot_with_button.py
tgbotzero/examples/02_bot_with_buttons.py
tgbotzero/examples/03_help.py
tgbotzero/examples/04_no_on_button_func_error.py
tgbotzero/examples/05_schedule_bot.py
tgbotzero/examples/06_on_start.py
tgbotzero/examples/07_commands.py
tgbotzero/examples/08_send_image.py
tgbotzero/examples/09_image_gallery.py
tgbotzero/examples/10_on_image.py
tgbotzero/examples/11_add_text_on_image.py
tgbotzero/examples/12_chat_id_bot.py
tgbotzero/examples/99_demo.py
tgbotzero/examples/__init__.py
tgbotzero/examples/cat.png
tgbotzero/examples/dog.png
tgbotzero/utils/__init__.py
tgbotzero/utils/botzero.py
tgbotzero/utils/check_on_button_functions.py
tgbotzero/utils/copy_examples.py
tgbotzero/utils/help.py
tgbotzero/utils/images.py
tgbotzero/utils/reply_markup.py
tgbotzero/utils/send_answer.py
tgbotzero-0.0.9.dist-info/LICENSE
tgbotzero-0.0.9.dist-info/METADATA
tgbotzero-0.0.9.dist-info/WHEEL
tgbotzero-0.0.9.dist-info/top_level.txt
tgbotzero-0.0.9.dist-info/RECORD
