Metadata-Version: 2.1
Name: tgbotzero
Version: 0.0.9
Summary: A zero-boilerplate simple telegram bots
Home-page: https://github.com/ShashkovS/tgbotzero
Author: Sergey Shashkov
Author-email: sh57@yandex.ru
License: MIT
Classifier: Development Status :: 4 - Beta
Classifier: Intended Audience :: Education
Classifier: Intended Audience :: End Users/Desktop
Classifier: License :: OSI Approved :: MIT License
Classifier: Natural Language :: Russian
Classifier: Operating System :: OS Independent
Classifier: Programming Language :: Python
Classifier: Programming Language :: Python :: 3
Classifier: Programming Language :: Python :: 3.7
Classifier: Programming Language :: Python :: 3.8
Classifier: Programming Language :: Python :: 3.9
Classifier: Programming Language :: Python :: 3.10
Classifier: Programming Language :: Python :: 3.11
Classifier: Programming Language :: Python :: 3.12
Classifier: Programming Language :: Python :: Implementation :: CPython
License-File: LICENSE
Requires-Dist: pyTelegramBotAPI
Requires-Dist: requests
Requires-Dist: Pillow
